{
  "checksum": "0cc961f41dbf4ff5ab5654751a4ba36e",
  "root": "rocambole@link-dev:./package.json",
  "node": {
    "rocambole@link-dev:./package.json": {
      "id": "rocambole@link-dev:./package.json",
      "name": "rocambole",
      "version": "link-dev:./package.json",
      "source": {
        "type": "link-dev",
        "path": ".",
        "manifest": "package.json"
      },
      "overrides": [],
      "dependencies": [
        "ocaml@4.7.1004@d41d8cd9", "@opam/dune@opam:1.8.2@511996a8"
      ],
      "devDependencies": []
    },
    "ocaml@4.7.1004@d41d8cd9": {
      "id": "ocaml@4.7.1004@d41d8cd9",
      "name": "ocaml",
      "version": "4.7.1004",
      "source": {
        "type": "install",
        "source": [
          "archive:https://registry.npmjs.org/ocaml/-/ocaml-4.7.1004.tgz#sha1:731ca0ddb4d845d2ed2da8af50f70c5ba9092114"
        ]
      },
      "overrides": [],
      "dependencies": [],
      "devDependencies": []
    },
    "@opam/dune@opam:1.8.2@511996a8": {
      "id": "@opam/dune@opam:1.8.2@511996a8",
      "name": "@opam/dune",
      "version": "opam:1.8.2",
      "source": {
        "type": "install",
        "source": [
          "archive:https://opam.ocaml.org/cache/md5/2b/2b7f45a6e14865f2318d34f12221ec1e#md5:2b7f45a6e14865f2318d34f12221ec1e",
          "archive:https://github.com/ocaml/dune/releases/download/1.8.2/dune-1.8.2.tbz#md5:2b7f45a6e14865f2318d34f12221ec1e"
        ],
        "opam": {
          "name": "dune",
          "version": "1.8.2",
          "path": "esy.lock/opam/dune.1.8.2"
        }
      },
      "overrides": [
        {
          "opamoverride":
            "esy.lock/overrides/opam__s__dune_opam__c__1.8.2_opam_override"
        }
      ],
      "dependencies": [
        "ocaml@4.7.1004@d41d8cd9", "@opam/base-unix@opam:base@87d0b2eb",
        "@opam/base-threads@opam:base@36803084",
        "@esy-ocaml/substs@0.0.1@d41d8cd9"
      ],
      "devDependencies": [
        "ocaml@4.7.1004@d41d8cd9", "@opam/base-unix@opam:base@87d0b2eb",
        "@opam/base-threads@opam:base@36803084"
      ]
    },
    "@opam/base-unix@opam:base@87d0b2eb": {
      "id": "@opam/base-unix@opam:base@87d0b2eb",
      "name": "@opam/base-unix",
      "version": "opam:base",
      "source": {
        "type": "install",
        "source": [ "no-source:" ],
        "opam": {
          "name": "base-unix",
          "version": "base",
          "path": "esy.lock/opam/base-unix.base"
        }
      },
      "overrides": [],
      "dependencies": [ "@esy-ocaml/substs@0.0.1@d41d8cd9" ],
      "devDependencies": []
    },
    "@opam/base-threads@opam:base@36803084": {
      "id": "@opam/base-threads@opam:base@36803084",
      "name": "@opam/base-threads",
      "version": "opam:base",
      "source": {
        "type": "install",
        "source": [ "no-source:" ],
        "opam": {
          "name": "base-threads",
          "version": "base",
          "path": "esy.lock/opam/base-threads.base"
        }
      },
      "overrides": [],
      "dependencies": [ "@esy-ocaml/substs@0.0.1@d41d8cd9" ],
      "devDependencies": []
    },
    "@esy-ocaml/substs@0.0.1@d41d8cd9": {
      "id": "@esy-ocaml/substs@0.0.1@d41d8cd9",
      "name": "@esy-ocaml/substs",
      "version": "0.0.1",
      "source": {
        "type": "install",
        "source": [
          "archive:https://registry.npmjs.org/@esy-ocaml/substs/-/substs-0.0.1.tgz#sha1:59ebdbbaedcda123fc7ed8fb2b302b7d819e9a46"
        ]
      },
      "overrides": [],
      "dependencies": [],
      "devDependencies": []
    }
  }
}